Metadata-Version: 2.1
Name: msicu-grading-dip
Version: 0.33
Summary: Grading for MSICU DIP class (Mexico)
Home-page: https://github.com/MSICUDIP
Author: Arturo Curiel
Author-email: me@arturocuriel.com
License: UNKNOWN
Platform: UNKNOWN
Classifier: Programming Language :: Python :: 3
Classifier: License :: OSI Approved :: MIT License
Classifier: Operating System :: OS Independent
